wradlib/__init__.py
wradlib/adjust.py
wradlib/atten.py
wradlib/classify.py
wradlib/comp.py
wradlib/dp.py
wradlib/ipol.py
wradlib/qual.py
wradlib/speedup.f
wradlib/trafo.py
wradlib/util.py
wradlib/verify.py
wradlib/version.py
wradlib/vis.py
wradlib/vpr.py
wradlib/xarray.py
wradlib/zonalstats.py
wradlib/zr.py
wradlib/georef/__init__.py
wradlib/georef/misc.py
wradlib/georef/polar.py
wradlib/georef/projection.py
wradlib/georef/raster.py
wradlib/georef/rect.py
wradlib/georef/satellite.py
wradlib/georef/vector.py
wradlib/georef/xarray.py
wradlib/io/__init__.py
wradlib/io/backends.py
wradlib/io/dem.py
wradlib/io/gdal.py
wradlib/io/hdf.py
wradlib/io/iris.py
wradlib/io/misc.py
wradlib/io/netcdf.py
wradlib/io/radolan.py
wradlib/io/rainbow.py
wradlib/io/xarray.py
wradlib/tests/__init__.py
wradlib/tests/conftest.py
wradlib/tests/test_adjust.py
wradlib/tests/test_atten.py
wradlib/tests/test_classify.py
wradlib/tests/test_comp.py
wradlib/tests/test_dp.py
wradlib/tests/test_georef.py
wradlib/tests/test_io.py
wradlib/tests/test_io_backends.py
wradlib/tests/test_ipol.py
wradlib/tests/test_qual.py
wradlib/tests/test_trafo.py
wradlib/tests/test_util.py
wradlib/tests/test_verify.py
wradlib/tests/test_vis.py
wradlib/tests/test_vpr.py
wradlib/tests/test_xarray.py
wradlib/tests/test_zonalstats.py
wradlib/tests/test_zr.py
wradlib-2.6.1.dist-info/METADATA
wradlib-2.6.1.dist-info/WHEEL
wradlib-2.6.1.dist-info/entry_points.txt
wradlib-2.6.1.dist-info/licenses/LICENSE-CC-BY-SA-4.0
wradlib-2.6.1.dist-info/licenses/LICENSE-MIT
wradlib-2.6.1.dist-info/licenses/LICENSE.txt
wradlib-2.6.1.dist-info/RECORD
