Metadata-Version: 2.4
Name: wradlib
Version: 2.6.1
Summary: wradlib - An Open Source Library for Weather Radar Data Processing
Project-URL: homepage, https://wradlib.org
Project-URL: documentation, https://docs.wradlib.org/
Project-URL: repository, https://github.com/wradlib/wradlib
Project-URL: changelog, https://docs.wradlib.org/en/stable/release_notes.html
Author-email: Kai Mühlbauer <kmuehlbauer@wradlib.org>, Maik Heistermann <heisterm@uni-potsdam.de>
Maintainer-email: wradlib developers <wradlib@wradlib.org>
License: # Licensing Overview
License-File: LICENSE-CC-BY-SA-4.0
License-File: LICENSE-MIT
License-File: LICENSE.txt
Classifier: Development Status :: 5 - Production/Stable
Classifier: Intended Audience :: Developers
Classifier: Intended Audience :: Education
Classifier: Intended Audience :: Science/Research
Classifier: License :: OSI Approved :: MIT License
Classifier: Operating System :: MacOS :: MacOS X
Classifier: Operating System :: Microsoft :: Windows
Classifier: Operating System :: POSIX :: Linux
Classifier: Programming Language :: Python
Classifier: Programming Language :: Python :: 3.10
Classifier: Programming Language :: Python :: 3.11
Classifier: Programming Language :: Python :: 3.12
Classifier: Programming Language :: Python :: 3.13
Classifier: Programming Language :: Python :: 3.14
Classifier: Topic :: Scientific/Engineering
Classifier: Topic :: Scientific/Engineering :: Atmospheric Science
Requires-Python: >=3.9
Requires-Dist: deprecation
Requires-Dist: matplotlib
Requires-Dist: numpy
Requires-Dist: packaging
Requires-Dist: pyproj
Requires-Dist: scipy
Requires-Dist: xarray>=2024.10.0
Requires-Dist: xradar>=0.8.0
Provides-Extra: dev
Requires-Dist: black; extra == 'dev'
Requires-Dist: bottleneck; extra == 'dev'
Requires-Dist: cartopy; extra == 'dev'
Requires-Dist: cmweather; extra == 'dev'
Requires-Dist: codecov; extra == 'dev'
Requires-Dist: coverage; extra == 'dev'
Requires-Dist: dask; extra == 'dev'
Requires-Dist: gdal>=3; extra == 'dev'
Requires-Dist: geopandas; extra == 'dev'
Requires-Dist: h5netcdf; extra == 'dev'
Requires-Dist: h5py; extra == 'dev'
Requires-Dist: netcdf4; extra == 'dev'
Requires-Dist: open-radar-data; extra == 'dev'
Requires-Dist: pre-commit; extra == 'dev'
Requires-Dist: pytest; extra == 'dev'
Requires-Dist: pytest-cov; extra == 'dev'
Requires-Dist: pytest-doctestplus; extra == 'dev'
Requires-Dist: pytest-sugar; extra == 'dev'
Requires-Dist: pytest-xdist; extra == 'dev'
Requires-Dist: requests; extra == 'dev'
Requires-Dist: rioxarray; extra == 'dev'
Requires-Dist: ruff; extra == 'dev'
Requires-Dist: wradlib-data; extra == 'dev'
Requires-Dist: xmltodict; extra == 'dev'
Provides-Extra: doc
Requires-Dist: black; extra == 'doc'
Requires-Dist: bottleneck; extra == 'doc'
Requires-Dist: cartopy; extra == 'doc'
Requires-Dist: cmweather; extra == 'doc'
Requires-Dist: codecov; extra == 'doc'
Requires-Dist: coverage; extra == 'doc'
Requires-Dist: dask; extra == 'doc'
Requires-Dist: gdal>=3; extra == 'doc'
Requires-Dist: geopandas; extra == 'doc'
Requires-Dist: h5netcdf; extra == 'doc'
Requires-Dist: h5py; extra == 'doc'
Requires-Dist: jupyter; extra == 'doc'
Requires-Dist: jupytext; extra == 'doc'
Requires-Dist: myst-nb; extra == 'doc'
Requires-Dist: nbformat; extra == 'doc'
Requires-Dist: netcdf4; extra == 'doc'
Requires-Dist: open-radar-data; extra == 'doc'
Requires-Dist: pre-commit; extra == 'doc'
Requires-Dist: pybtex; extra == 'doc'
Requires-Dist: pytest; extra == 'doc'
Requires-Dist: pytest-cov; extra == 'doc'
Requires-Dist: pytest-doctestplus; extra == 'doc'
Requires-Dist: pytest-sugar; extra == 'doc'
Requires-Dist: pytest-xdist; extra == 'doc'
Requires-Dist: requests; extra == 'doc'
Requires-Dist: rioxarray; extra == 'doc'
Requires-Dist: ruff; extra == 'doc'
Requires-Dist: sphinx; extra == 'doc'
Requires-Dist: sphinx-book-theme>=1.0; extra == 'doc'
Requires-Dist: sphinx-copybutton; extra == 'doc'
Requires-Dist: sphinxcontrib-bibtex; extra == 'doc'
Requires-Dist: wradlib-data; extra == 'doc'
Requires-Dist: xmltodict; extra == 'doc'
Provides-Extra: opt
Requires-Dist: bottleneck; extra == 'opt'
Requires-Dist: cartopy; extra == 'opt'
Requires-Dist: cmweather; extra == 'opt'
Requires-Dist: dask; extra == 'opt'
Requires-Dist: gdal>=3; extra == 'opt'
Requires-Dist: geopandas; extra == 'opt'
Requires-Dist: h5netcdf; extra == 'opt'
Requires-Dist: h5py; extra == 'opt'
Requires-Dist: netcdf4; extra == 'opt'
Requires-Dist: requests; extra == 'opt'
Requires-Dist: rioxarray; extra == 'opt'
Requires-Dist: xmltodict; extra == 'opt'
